{
  "info": {
    "key": "g767_0119"
  },
  "sheets": {
    "מזומנים": {
      "columns": [
        "שם נ\"ע",
        "מספר ני\"ע",
        "מספר מנפיק",
        "דירוג",
        "שם מדרג",
        "סוג מטבע",
        "שיעור ריבית",
        "תשואה לפידיון",
        "שווי שוק",
        "שיעור מנכסי אפיק ה השקעה",
        "שעור מנכסי השקעה"
      ],
      "data": [
        [
          "מזומן (מזרחי)",
          4,
          20,
          "AAA IL",
          "מעלות",
          "שקל חדש",
          "",
          "",
          31932.03,
          3.3605,
          0.2378
        ],
        [
          "מזומן (הבינלאומי)",
          4,
          31,
          "AA+ IL",
          "S&P מעלות",
          "שקל חדש",
          "",
          "",
          118628.89,
          12.4844,
          0.8835
        ],
        [
          "מזומן מחוץ למזרחי (מזרחי)",
          419259239,
          20,
          "AAA IL",
          "מעלות",
          "שקל חדש",
          "",
          "",
          3.96,
          0.0004,
          0.0
        ],
        [
          "מזומן אירו (מזרחי)",
          1010,
          20,
          "AAA IL",
          "מעלות",
          "אירו",
          "",
          "",
          14941.22,
          1.5724,
          0.1113
        ],
        [
          "מזומן אירו (הבינלאומי)",
          1010,
          31,
          "AA+ IL",
          "S&P מעלות",
          "אירו",
          "",
          "",
          20327.98,
          2.1393,
          0.1514
        ],
        [
          "מזומן דולר אמריקאי (מזרחי)",
          14,
          20,
          "AAA IL",
          "מעלות",
          "דולר אמריקאי",
          "",
          "",
          382333.16,
          40.2365,
          2.8476
        ],
        [
          "מזומן דולר אמריקאי (הבינלאומי)",
          14,
          31,
          "AA+ IL",
          "S&P מעלות",
          "דולר אמריקאי",
          "",
          "",
          426205.16,
          44.8535,
          3.1743
        ],
        [
          "מזומן יין יפני (מזרחי)",
          1002,
          20,
          "AAA IL",
          "מעלות",
          "יין יפני",
          "",
          "",
          3794.8,
          0.3994,
          0.0283
        ],
        [
          "מזומן יין יפני (הבינלאומי)",
          1002,
          31,
          "AA+ IL",
          "S&P מעלות",
          "יין יפני",
          "",
          "",
          2651.98,
          0.2791,
          0.0198
        ],
        [
          "מזומן לירה שטרלינג (מזרחי)",
          1004,
          20,
          "AAA IL",
          "מעלות",
          "לירה שטרלינג",
          "",
          "",
          -19283.92,
          -2.0294,
          -0.1436
        ],
        [
          "מזומן לירה שטרלינג (הבינלאומי)",
          1004,
          31,
          "AA+ IL",
          "S&P מעלות",
          "לירה שטרלינג",
          "",
          "",
          1154.15,
          0.1215,
          0.0086
        ],
        [
          "מזומן מקסיקו פזו (מזרחי)",
          1021,
          20,
          "AAA IL",
          "מעלות",
          "מקסיקו פזו",
          "",
          "",
          5.27,
          0.0006,
          0.0
        ],
        [
          "HSBC USD",
          "HSBC USD",
          "",
          "AA-",
          "Fitch",
          "דולר אמריקאי",
          "",
          "",
          3949.19,
          0.4156,
          0.0294
        ]
      ]
    },
    "תעודות התחייבות ממשלתיות": {
      "columns": [
        "שם נ\"ע",
        "מספר ני\"ע",
        "זירת מסחר",
        "דירוג",
        "שם מדרג",
        "תאריך רכישה",
        "מח\"מ",
        "סוג מטבע",
        "שיעור ריבית",
        "תשואה לפידיון",
        "ערך נקוב",
        "שער",
        "פידיון/ריבית לקבל",
        "שווי שוק",
        "שעור מערך נקוב מונפק",
        "שיעור מנכסי אפיק ההשקעה",
        "שעור מנכסי השקעה"
      ],
      "data": [
        [
          "גליל 5903",
          9590332,
          "TASE",
          "RF",
          "",
          "",
          2.23,
          "שקל חדש",
          0.04,
          -0.0117,
          6513151.0,
          150.09,
          0,
          9775.59,
          0.0004,
          0.0784,
          0.0728
        ],
        [
          "גליל 5904",
          9590431,
          "TASE",
          "RF",
          "",
          "",
          4.86,
          "שקל חדש",
          0.04,
          -0.0047,
          465.0,
          156.8,
          0,
          0.73,
          0.0,
          0.0,
          0.0
        ],
        [
          "ממשל צמודה 0545",
          1134865,
          "TASE",
          "RF",
          "",
          "",
          22.74,
          "שקל חדש",
          0.01,
          0.0148,
          3872430.0,
          91.35,
          0,
          3537.46,
          0.0003,
          0.0284,
          0.0263
        ],
        [
          "ממשל צמודה 0841",
          1120583,
          "TASE",
          "RF",
          "",
          "",
          17.59,
          "שקל חדש",
          0.0275,
          0.012,
          785849.0,
          141.23,
          0,
          1109.85,
          0.0,
          0.0089,
          0.0083
        ],
        [
          "ממשל צמודה 1019",
          1114750,
          "TASE",
          "RF",
          "",
          "",
          0.58,
          "שקל חדש",
          0.03,
          -0.0206,
          3339549.0,
          114.9,
          0,
          3837.14,
          0.0002,
          0.0308,
          0.0286
        ],
        [
          "ממשל צמודה 1020",
          1137181,
          "TASE",
          "RF",
          "",
          "",
          1.58,
          "שקל חדש",
          0.001,
          -0.0135,
          7356633.0,
          103.3,
          0,
          7599.4,
          0.0005,
          0.0609,
          0.0566
        ],
        [
          "ממשלתי צמוד 0527",
          1140847,
          "TASE",
          "RF",
          "",
          "",
          7.92,
          "שקל חדש",
          0.0075,
          -0.0004,
          528135.0,
          108.29,
          0,
          571.92,
          0.0,
          0.0046,
          0.0043
        ],
        [
          "ממשלתי צמוד 0536",
          1097708,
          "TASE",
          "RF",
          "",
          "",
          13.36,
          "שקל חדש",
          0.04,
          0.0087,
          1176057.0,
          182.1,
          0,
          2141.6,
          0.0001,
          0.0172,
          0.016
        ],
        [
          "ממשלתי צמוד 0922",
          1124056,
          "TASE",
          "RF",
          "",
          "",
          3.36,
          "שקל חדש",
          0.0275,
          -0.0087,
          548465.0,
          118.48,
          0,
          649.82,
          0.0,
          0.0052,
          0.0048
        ],
        [
          "ממשלתי צמוד 0923",
          1128081,
          "TASE",
          "RF",
          "",
          "",
          4.34,
          "שקל חדש",
          0.0175,
          -0.0063,
          975729.0,
          113.75,
          0,
          1109.89,
          0.0001,
          0.0089,
          0.0083
        ],
        [
          "מ.ק.מ.     1119",
          8191116,
          "TASE",
          "RF",
          "",
          "",
          0.6,
          "שקל חדש",
          "",
          0.0027,
          9296196.0,
          99.84,
          0,
          9281.32,
          0.001,
          0.0744,
          0.0691
        ],
        [
          "מ.ק.מ.  819",
          8190811,
          "TASE",
          "RF",
          "",
          "",
          0.35,
          "שקל חדש",
          "",
          0.0026,
          8748397.0,
          99.91,
          0,
          8740.52,
          0.001,
          0.0701,
          0.0651
        ],
        [
          "מ.ק.מ. 120",
          8200123,
          "TASE",
          "RF",
          "",
          "",
          0.77,
          "שקל חדש",
          "",
          0.0027,
          5000000.0,
          99.79,
          0,
          4989.5,
          0.0006,
          0.04,
          0.0372
        ],
        [
          "מק\"מ",
          8190613,
          "TASE",
          "RF",
          "",
          "",
          0.18,
          "שקל חדש",
          "",
          0.0022,
          178667.0,
          99.96,
          0,
          178.6,
          0.0,
          0.0014,
          0.0013
        ],
        [
          "מק\"מ",
          8191017,
          "TASE",
          "RF",
          "",
          "",
          0.51,
          "שקל חדש",
          "",
          0.0028,
          1420323.0,
          99.86,
          0,
          1418.33,
          0.0002,
          0.0114,
          0.0106
        ],
        [
          "מק\"מ 1219",
          8191215,
          "TASE",
          "RF",
          "",
          "",
          0.68,
          "שקל חדש",
          "",
          0.0027,
          11005664.0,
          99.82,
          0,
          10985.85,
          0.0012,
          0.0881,
          0.0818
        ],
        [
          "מק\"מ 419",
          8190415,
          "TASE",
          "RF",
          "",
          "",
          0.01,
          "שקל חדש",
          "",
          0.0184,
          661704.0,
          99.99,
          0,
          661.64,
          0.0001,
          0.0053,
          0.0049
        ],
        [
          "מק\"מ 529",
          8190522,
          "TASE",
          "RF",
          "",
          "",
          0.1,
          "שקל חדש",
          "",
          0.003,
          8149543.0,
          99.97,
          0,
          8147.1,
          0.0007,
          0.0653,
          0.0607
        ],
        [
          "מק\"מ 719",
          8190712,
          "TASE",
          "RF",
          "",
          "",
          0.25,
          "שקל חדש",
          "",
          0.0031,
          1100000.0,
          99.92,
          0,
          1099.12,
          0.0001,
          0.0088,
          0.0082
        ],
        [
          "מק\"מ 919",
          8190910,
          "TASE",
          "RF",
          "",
          "",
          0.43,
          "שקל חדש",
          "",
          0.0028,
          5464000.0,
          99.88,
          0,
          5457.44,
          0.0006,
          0.0438,
          0.0406
        ],
        [
          "ממשל קצרה 11/19",
          1157098,
          "TASE",
          "RF",
          "",
          "",
          0.66,
          "שקל חדש",
          "",
          0.0032,
          644008.0,
          99.79,
          0,
          642.66,
          0.0006,
          0.0052,
          0.0048
        ],
        [
          "ממשל שקלי 1123",
          1155068,
          "TASE",
          "RF",
          "",
          "",
          4.52,
          "שקל חדש",
          0.015,
          0.0108,
          432077.0,
          102.39,
          0,
          442.4,
          0.0001,
          0.0035,
          0.0033
        ],
        [
          "ממשל שקלית 0121",
          1142223,
          "TASE",
          "RF",
          "",
          "",
          1.83,
          "שקל חדש",
          0.005,
          0.0048,
          4559177.0,
          100.12,
          0,
          4564.65,
          0.0003,
          0.0366,
          0.034
        ],
        [
          "ממשל שקלית 0122",
          1123272,
          "TASE",
          "RF",
          "",
          "",
          2.7,
          "שקל חדש",
          0.055,
          0.0067,
          2803067.0,
          114.42,
          0,
          3207.27,
          0.0002,
          0.0257,
          0.0239
        ],
        [
          "ממשל שקלית 0142",
          1125400,
          "TASE",
          "RF",
          "",
          "",
          15.11,
          "שקל חדש",
          0.055,
          0.0277,
          353761.0,
          146.6,
          0,
          518.61,
          0.0,
          0.0042,
          0.0039
        ],
        [
          "ממשל שקלית 0323",
          1126747,
          "TASE",
          "RF",
          "",
          "",
          3.78,
          "שקל חדש",
          0.0425,
          0.0094,
          240651.0,
          112.96,
          0,
          271.84,
          0.0,
          0.0022,
          0.002
        ],
        [
          "ממשל שקלית 0421",
          1138130,
          "TASE",
          "RF",
          "",
          "",
          2.05,
          "שקל חדש",
          0.01,
          0.0051,
          1167995.0,
          101.93,
          0,
          1190.54,
          0.0001,
          0.0095,
          0.0089
        ],
        [
          "ממשל שקלית 0519",
          1131770,
          "TASE",
          "RF",
          "",
          "",
          0.16,
          "שקל חדש",
          0.0225,
          0.0024,
          33603.0,
          102.21,
          0,
          34.35,
          0.0,
          0.0003,
          0.0003
        ],
        [
          "ממשל שקלית 0928",
          1150879,
          "TASE",
          "RF",
          "",
          "",
          8.59,
          "שקל חדש",
          0.0225,
          0.0183,
          6706543.42,
          104.76,
          0,
          7025.77,
          0.0007,
          0.0563,
          0.0523
        ],
        [
          "ממשל שקלית 1122",
          1141225,
          "TASE",
          "RF",
          "",
          "",
          3.6,
          "שקל חדש",
          0.0125,
          0.0087,
          607865.0,
          101.77,
          0,
          618.62,
          0.0001,
          0.005,
          0.0046
        ],
        [
          "ממשלתי שקלי 0347",
          1140193,
          "TASE",
          "RF",
          "",
          "",
          18.41,
          "שקל חדש",
          0.0375,
          0.031,
          3460993.0,
          112.1,
          0,
          3879.77,
          0.0003,
          0.0311,
          0.0289
        ],
        [
          "ממשלתי שקלי 0825",
          1135557,
          "TASE",
          "RF",
          "",
          "",
          6.08,
          "שקל חדש",
          0.0175,
          0.014,
          2038056.0,
          103.15,
          0,
          2102.25,
          0.0001,
          0.0169,
          0.0157
        ],
        [
          "ממשל משתנה 0520",
          1116193,
          "TASE",
          "RF",
          "",
          "",
          1.17,
          "שקל חדש",
          0.002924,
          0.0029,
          3688905.0,
          100.02,
          0,
          3689.64,
          0.0002,
          0.0296,
          0.0275
        ],
        [
          "ממשל משתנה 0526",
          1141795,
          "TASE",
          "RF",
          "",
          "",
          7.1,
          "שקל חדש",
          0.002924,
          0.0038,
          1356956.0,
          99.36,
          0,
          1348.27,
          0.0002,
          0.0108,
          0.01
        ],
        [
          "ממשל משתנה 1121",
          1127646,
          "TASE",
          "RF",
          "",
          "",
          2.66,
          "שקל חדש",
          0.002924,
          0.0033,
          13546149.0,
          99.92,
          0,
          13535.31,
          0.001,
          0.1085,
          0.1008
        ],
        [
          "ISRAE 3.1 06/23",
          "US4651387M19",
          "אחר",
          "A1",
          "Moody's",
          "",
          3.98,
          "דולר אמריקאי",
          0.0315,
          0.0274,
          97000.0,
          102.51,
          0,
          361.14,
          0.0001,
          0.0029,
          0.0027
        ]
      ]
    },
    "אופציות": {
      "columns": [
        "שם נ\"ע",
        "מספר ני\"ע",
        "זירת מסחר",
        "ענף מסחר",
        "סוג מטבע",
        "ערך נקוב",
        "שער",
        "שווי שוק",
        "שעור מערך נקוב מונפק",
        "שיעור מנכסי אפיק ההשקעה",
        "שעור מנכסי השקעה"
      ],
      "data": [
        [
          "C 1530 APR",
          82645532,
          "TASE",
          "ל.ר.",
          "שקל חדש",
          132,
          313000,
          413.16,
          "",
          2.112,
          0.0031
        ],
        [
          "P 1530 APR",
          82646175,
          "TASE",
          "ל.ר.",
          "שקל חדש",
          -132,
          164800,
          -217.54,
          "",
          -1.112,
          -0.0016
        ]
      ]
    },
    "חוזים עתידיים": {
      "columns": [
        "שם נ\"ע",
        "מספר ני\"ע",
        "זירת מסחר",
        "ענף מסחר",
        "סוג מטבע",
        "ערך נקוב",
        "שער",
        "שווי שוק",
        "שיעור מנכסי אפיק ההשקעה",
        "שעור מנכסי השקעה"
      ],
      "data": [
        [
          "F 06/16 EUROBOND",
          "RXM9",
          "אחר",
          "ל.ר.",
          "אירו",
          -3,
          16634,
          -41.54,
          -0.1574,
          -0.0003
        ],
        [
          "F 06/19 NIKKEI 225",
          "NXM9",
          "אחר",
          "ל.ר.",
          "דולר אמריקאי",
          9,
          2128500,
          -52.3,
          -0.1982,
          -0.0004
        ],
        [
          "F 09/19 DTB EURO STOXX 50",
          "VGM9",
          "אחר",
          "ל.ר.",
          "אירו",
          30,
          327200,
          79.52,
          0.3013,
          0.0006
        ],
        [
          "F 6/19 FTSE",
          "Z M9",
          "אחר",
          "ל.ר.",
          "לירה שטרלינג",
          2,
          721150,
          13.54,
          0.0513,
          0.0001
        ],
        [
          "F 6/19 MINI DAX",
          "DFWM9",
          "אחר",
          "ל.ר.",
          "אירו",
          2,
          1153450,
          -0.47,
          -0.0018,
          0.0
        ],
        [
          "F 6/19 MINI S&P",
          "ESM9",
          "אחר",
          "ל.ר.",
          "דולר אמריקאי",
          28,
          283775,
          247.88,
          0.9392,
          0.0018
        ],
        [
          "F6/19 MSCI",
          "MESM9",
          "אחר",
          "ל.ר.",
          "דולר אמריקאי",
          17,
          105740,
          17.29,
          0.0655,
          0.0001
        ]
      ]
    },
    "לא סחיר - אופציות": {
      "columns": [
        "שם נ\"ע",
        "מספר ני\"ע",
        "ענף מסחר",
        "תאריך רכישה",
        "סוג מטבע",
        "ערך נקוב",
        "שער",
        "שווי הוגן",
        "שעור מערך נקוב מונפק",
        "שיעור מנכסי אפיק ההשקעה",
        "שעור מנכסי השקעה"
      ],
      "data": [
        [
          "C 260619 USD/NIS3.65",
          402587182,
          "ל.ר.",
          "26/03/2019",
          "שקל חדש",
          -183000,
          2.19,
          -4,
          "",
          1,
          0
        ]
      ]
    },
    "לא סחיר - חוזים עתידיים": {
      "columns": [
        "שם נ\"ע",
        "מספר ני\"ע",
        "ענף מסחר",
        "תאריך רכישה",
        "סוג מטבע",
        "ערך נקוב",
        "שער",
        "שווי הוגן",
        "שיעור מנכסי אפיק ההשקעה",
        "שעור מנכסי השקעה"
      ],
      "data": [
        [
          "FW USD/ILS 22/05/19 3.5976 סיטי",
          777105016,
          "ל.ר.",
          "",
          "שקל חדש",
          -79760.0,
          1.95,
          -1.55,
          0.0085,
          0.0
        ],
        [
          "FW030419 USD/NIS3.60",
          434558292,
          "ל.ר.",
          "6/02/2019",
          "שקל חדש",
          -60390.0,
          2.65,
          -1.6,
          0.0088,
          0.0
        ],
        [
          "FW030419 USD/NIS3.74",
          433539897,
          "ל.ר.",
          "17/12/2018",
          "שקל חדש",
          714500.0,
          -11.22,
          -80.15,
          0.4384,
          -0.0006
        ],
        [
          "FW050619 USD/NIS3.60",
          435231550,
          "ל.ר.",
          "12/03/2019",
          "שקל חדש",
          522390.0,
          1.59,
          8.31,
          -0.0455,
          0.0001
        ],
        [
          "FW100419 USD/NIS3.60",
          435158035,
          "ל.ר.",
          "7/03/2019",
          "שקל חדש",
          -128000.0,
          2.51,
          -3.22,
          0.0176,
          0.0
        ],
        [
          "FW100419 USD/NIS3.67",
          433924800,
          "ל.ר.",
          "7/01/2019",
          "שקל חדש",
          1297500.0,
          -4.14,
          -53.65,
          0.2935,
          -0.0004
        ],
        [
          "FW190619 USD/NIS3.58",
          435342969,
          "ל.ר.",
          "18/03/2019",
          "שקל חדש",
          201000.0,
          3.58,
          7.2,
          -0.0394,
          0.0001
        ],
        [
          "FW220519 USD/NIS3.60",
          434757860,
          "ל.ר.",
          "18/02/2019",
          "שקל חדש",
          365400.0,
          2.16,
          7.91,
          -0.0432,
          0.0001
        ],
        [
          "FW100719 USD/JPY110.",
          435035001,
          "ל.ר.",
          "4/03/2019",
          "יין יפני",
          -125451.26,
          -86.73,
          3.57,
          -0.0195,
          0.0
        ],
        [
          "FW120619 GBP/USD1.33",
          435343587,
          "ל.ר.",
          "18/03/2019",
          "דולר אמריקאי",
          29000.0,
          -2.22,
          -2.34,
          0.0128,
          0.0
        ],
        [
          "FW150519 EUR/USD1.13",
          435513205,
          "ל.ר.",
          "27/03/2019",
          "דולר אמריקאי",
          -40000.0,
          -0.5,
          0.73,
          -0.004,
          0.0
        ],
        [
          "FW150519 EUR/USD1.14",
          434622429,
          "ל.ר.",
          "11/02/2019",
          "דולר אמריקאי",
          -38000.0,
          -1.16,
          1.6,
          -0.0088,
          0.0
        ],
        [
          "FW150519 EUR/USD1.14",
          435120647,
          "ל.ר.",
          "6/03/2019",
          "דולר אמריקאי",
          -87000.0,
          -0.96,
          3.03,
          -0.0166,
          0.0
        ],
        [
          "FW150519 EUR/USD1.15",
          434462610,
          "ל.ר.",
          "4/02/2019",
          "דולר אמריקאי",
          498600.0,
          -2.7,
          -48.84,
          0.2671,
          -0.0004
        ],
        [
          "IRS  סיטי1.335 928",
          777105107,
          "ל.ר.",
          "",
          "שקל חדש",
          1250000.0,
          -1.07,
          -13.32,
          0.0728,
          -0.0001
        ],
        [
          "IR140119 NIS/NIS1.99",
          402508162,
          "ל.ר.",
          "",
          "שקל חדש",
          300000.0,
          -3.5,
          -10.51,
          0.0575,
          -0.0001
        ]
      ]
    },
    "השקעות אחרות": {
      "columns": [
        "שם נ\"ע",
        "מספר ני\"ע",
        "דירוג",
        "שם מדרג",
        "סוג מטבע",
        "שיעור ריבית",
        "תשואה לפידיון",
        "שווי הוגן",
        "שיעור מנכסי אפיק ה השקעה",
        "שעור מנכסי השקעה"
      ],
      "data": [
        [
          "מעבר פקדונות - בינלאומי יורו",
          419259429,
          "AA+ IL",
          "S&P מעלות",
          "אירו",
          "",
          "",
          -100.94,
          0.4302,
          -0.0008
        ],
        [
          "הפרשי מיזוג איילון בינלאומי",
          419259551,
          "NR IL",
          "",
          "שקל חדש",
          "",
          "",
          -7.52,
          0.0321,
          -0.0001
        ],
        [
          "מעבר פקדונות",
          419256003,
          "NR IL",
          "",
          "שקל חדש",
          "",
          "",
          -0.1,
          0.0004,
          0.0
        ],
        [
          "בנק מעבר נכסים-דולר",
          419259312,
          "NR",
          "",
          "דולר אמריקאי",
          "",
          "",
          -126.07,
          0.5373,
          -0.0009
        ]
      ]
    }
  }
}